jet_guestbook/__init__.py
jet_guestbook/__version__.py
jet_guestbook/app/__init__.py
jet_guestbook/app/_common.py
jet_guestbook/app/controller.py
jet_guestbook/app/visit/__init__.py
jet_guestbook/app/visit/models.py
jet_guestbook/app/visit/schemas.py
jet_guestbook/app/visit/service.py
jet_guestbook/app/visitor/__init__.py
jet_guestbook/app/visitor/models.py
jet_guestbook/app/visitor/schemas.py
jet_guestbook/app/visitor/service.py
jet_guestbook-0.1.0.dist-info/LICENSE
jet_guestbook-0.1.0.dist-info/METADATA
jet_guestbook-0.1.0.dist-info/WHEEL
jet_guestbook-0.1.0.dist-info/entry_points.txt
jet_guestbook-0.1.0.dist-info/top_level.txt
jet_guestbook-0.1.0.dist-info/RECORD
